jonoer/__init__.py
jonoer/jonoer.py
jonoer-0.2.0.dist-info/METADATA
jonoer-0.2.0.dist-info/WHEEL
jonoer-0.2.0.dist-info/top_level.txt
jonoer-0.2.0.dist-info/RECORD
