Metadata-Version: 2.4
Name: jonoer
Version: 0.2.0
Summary: Мемный набор модулей с гимнами, странными и абсурдными эффектами
Author: Андрей
Author-email: danya10121985@gmail.com
Classifier: Programming Language :: Python :: 3
Classifier: License :: OSI Approved :: MIT License
Classifier: Operating System :: OS Independent
Requires-Python: >=3.6
Requires-Dist: sounddevice
Requires-Dist: numpy
Dynamic: author
Dynamic: author-email
Dynamic: classifier
Dynamic: requires-dist
Dynamic: requires-python
Dynamic: summary
